SuperconGAN/__init__.py
SuperconGAN/evaluate.py
SuperconGAN/model.py
SuperconGAN/validate.py
tests/__init__.py
tests/test_1.py
SuperconGAN-0.2.5.dist-info/LICENSE
SuperconGAN-0.2.5.dist-info/METADATA
SuperconGAN-0.2.5.dist-info/WHEEL
SuperconGAN-0.2.5.dist-info/top_level.txt
SuperconGAN-0.2.5.dist-info/RECORD
