Metadata-Version: 2.1
Name: SuperconGAN
Version: 0.2.5
Summary: GAN trained on superconductivity data
Home-page: https://github.com/RajeevAtla/SuperconGAN
Author: Rajeev Atla
Author-email: rajeev@rajeevatla.com
License: MIT Licence
Platform: UNKNOWN
Classifier: Programming Language :: Python :: 3
Classifier: License :: OSI Approved :: MIT License
Classifier: Natural Language :: English
Classifier: Operating System :: OS Independent
Requires-Python: >=3.6
Requires-Dist: ctgan
Requires-Dist: sdv
Requires-Dist: torch (<2,>=1.0)
Requires-Dist: torchvision (<1,>=0.4.2)
Requires-Dist: scikit-learn (==0.24.1)
Requires-Dist: numpy (==1.20.1)
Requires-Dist: pandas (<2,>=0.24)
Requires-Dist: rdt (<=0.4.0,>=0.2.7)
Requires-Dist: packaging
